{
  "0": {
    "serverName": "Augury Rock",
    "idWorld": 2103,
    "date": "25/11/2022",
    "time": "20:49:03",
    "worldColor": "blue",
    "nbKills": 0,
    "nbDeaths": 0,
    "ratio": 0,
    "skirmishKills": 0,
    "skirmishDeaths": 0,
    "skirmishRatio": 0,
    "Center": {
      "nbKills": 0,
      "nbDeaths": 0,
      "ratio": 0,
      "skirmishKills": 0,
      "skirmishDeaths": 0,
      "skirmishRatio": 0
    },
    "RedHome": {
      "nbKills": 0,
      "nbDeaths": 0,
      "ratio": 0,
      "skirmishKills": 0,
      "skirmishDeaths": 0,
      "skirmishRatio": 0
    },
    "BlueHome": {
      "nbKills": 0,
      "nbDeaths": 0,
      "ratio": 0,
      "skirmishKills": 0,
      "skirmishDeaths": 0,
      "skirmishRatio": 0
    },
    "GreenHome": {
      "nbKills": 0,
      "nbDeaths": 0,
      "ratio": 0,
      "skirmishKills": 0,
      "skirmishDeaths": 0,
      "skirmishRatio": 0
    },
    "skirmishScore": {
      "1": "red",
      "2": "green",
      "3": "blue"
    }
  },
  "1": {
    "serverName": "Augury Rock",
    "idWorld": 2103,
    "date": "25/11/2022",
    "time": "22:48:50",
    "worldColor": "blue",
    "nbKills": 1818,
    "nbDeaths": 2460,
    "ratio": 0.7390243902439024,
    "skirmishKills": 1818,
    "skirmishDeaths": 2460,
    "skirmishRatio": 0.7390243902439024,
    "Center": {
      "nbKills": 664,
      "nbDeaths": 685,
      "ratio": 0.969,
      "skirmishKills": 664,
      "skirmishDeaths": 685,
      "skirmishRatio": 0.9693430656934306
    },
    "RedHome": {
      "nbKills": 54,
      "nbDeaths": 127,
      "ratio": 0.425,
      "skirmishKills": 54,
      "skirmishDeaths": 127,
      "skirmishRatio": 0.4251968503937008
    },
    "BlueHome": {
      "nbKills": 720,
      "nbDeaths": 881,
      "ratio": 0.817,
      "skirmishKills": 720,
      "skirmishDeaths": 881,
      "skirmishRatio": 0.8172531214528944
    },
    "GreenHome": {
      "nbKills": 380,
      "nbDeaths": 767,
      "ratio": 0.495,
      "skirmishKills": 380,
      "skirmishDeaths": 767,
      "skirmishRatio": 0.4954367666232073
    },
    "skirmishScore": {
      "1": "green",
      "2": "red",
      "3": "blue"
    }
  },
  "2": {
    "serverName": "Augury Rock",
    "idWorld": 2103,
    "date": "26/11/2022",
    "time": "00:49:01",
    "worldColor": "blue",
    "nbKills": 2046,
    "nbDeaths": 3058,
    "ratio": 0.6690647482014388,
    "skirmishKills": 228,
    "skirmishDeaths": 598,
    "skirmishRatio": 0.38127090301003347,
    "Center": {
      "nbKills": 767,
      "nbDeaths": 806,
      "ratio": 0.952,
      "skirmishKills": 103,
      "skirmishDeaths": 121,
      "skirmishRatio": 0.8512396694214877
    },
    "RedHome": {
      "nbKills": 76,
      "nbDeaths": 148,
      "ratio": 0.514,
      "skirmishKills": 22,
      "skirmishDeaths": 21,
      "skirmishRatio": 1.0476190476190477
    },
    "BlueHome": {
      "nbKills": 807,
      "nbDeaths": 1274,
      "ratio": 0.633,
      "skirmishKills": 87,
      "skirmishDeaths": 393,
      "skirmishRatio": 0.22137404580152673
    },
    "GreenHome": {
      "nbKills": 396,
      "nbDeaths": 830,
      "ratio": 0.477,
      "skirmishKills": 16,
      "skirmishDeaths": 63,
      "skirmishRatio": 0.25396825396825395
    },
    "skirmishScore": {
      "1": "green",
      "2": "red",
      "3": "blue"
    }
  },
  "3": {
    "serverName": "Augury Rock",
    "idWorld": 2103,
    "date": "26/11/2022",
    "time": "03:42:52",
    "worldColor": "blue",
    "nbKills": 2113,
    "nbDeaths": 3179,
    "ratio": 0.6646744259201006,
    "skirmishKills": 67,
    "skirmishDeaths": 121,
    "skirmishRatio": 0.5537190082644629,
    "Center": {
      "nbKills": 789,
      "nbDeaths": 859,
      "ratio": 0.919,
      "skirmishKills": 22,
      "skirmishDeaths": 53,
      "skirmishRatio": 0.41509433962264153
    },
    "RedHome": {
      "nbKills": 84,
      "nbDeaths": 168,
      "ratio": 0.5,
      "skirmishKills": 8,
      "skirmishDeaths": 20,
      "skirmishRatio": 0.4
    },
    "BlueHome": {
      "nbKills": 840,
      "nbDeaths": 1310,
      "ratio": 0.641,
      "skirmishKills": 33,
      "skirmishDeaths": 36,
      "skirmishRatio": 0.9166666666666666
    },
    "GreenHome": {
      "nbKills": 400,
      "nbDeaths": 842,
      "ratio": 0.475,
      "skirmishKills": 4,
      "skirmishDeaths": 12,
      "skirmishRatio": 0.3333333333333333
    },
    "skirmishScore": {
      "1": "green",
      "2": "red",
      "3": "blue"
    }
  },
  "4": {
    "serverName": "Augury Rock",
    "idWorld": 2103,
    "date": "26/11/2022",
    "time": "04:48:49",
    "worldColor": "blue",
    "nbKills": 2115,
    "nbDeaths": 3182,
    "ratio": 0.664676304211188,
    "skirmishKills": 2,
    "skirmishDeaths": 3,
    "skirmishRatio": 0.6666666666666666,
    "Center": {
      "nbKills": 789,
      "nbDeaths": 861,
      "ratio": 0.916,
      "skirmishKills": 0,
      "skirmishDeaths": 2,
      "skirmishRatio": 0.0
    },
    "RedHome": {
      "nbKills": 85,
      "nbDeaths": 168,
      "ratio": 0.506,
      "skirmishKills": 1,
      "skirmishDeaths": 0,
      "skirmishRatio": 1
    },
    "BlueHome": {
      "nbKills": 840,
      "nbDeaths": 1311,
      "ratio": 0.641,
      "skirmishKills": 0,
      "skirmishDeaths": 1,
      "skirmishRatio": 0.0
    },
    "GreenHome": {
      "nbKills": 401,
      "nbDeaths": 842,
      "ratio": 0.476,
      "skirmishKills": 1,
      "skirmishDeaths": 0,
      "skirmishRatio": 1
    },
    "skirmishScore": {
      "1": "red",
      "2": "green",
      "3": "blue"
    }
  }
}