{
  "84": {
    "serverName": "Augury Rock",
    "idWorld": 2103,
    "date": "23/09/2022",
    "time": "19:58:14",
    "worldColor": "green",
    "nbKills": 36464,
    "nbDeaths": 39814,
    "ratio": 0.9158587431556738,
    "skirmishKills": 0,
    "skirmishDeaths": 0,
    "skirmishRatio": 0,
    "Center": {
      "nbKills": 13719,
      "nbDeaths": 16249,
      "ratio": 0.844,
      "skirmishKills": 0,
      "skirmishDeaths": 0,
      "skirmishRatio": 0
    },
    "RedHome": {
      "nbKills": 3168,
      "nbDeaths": 4420,
      "ratio": 0.717,
      "skirmishKills": 0,
      "skirmishDeaths": 0,
      "skirmishRatio": 0
    },
    "BlueHome": {
      "nbKills": 6594,
      "nbDeaths": 8716,
      "ratio": 0.757,
      "skirmishKills": 0,
      "skirmishDeaths": 0,
      "skirmishRatio": 0
    },
    "GreenHome": {
      "nbKills": 12983,
      "nbDeaths": 10429,
      "ratio": 1.245,
      "skirmishKills": 0,
      "skirmishDeaths": 0,
      "skirmishRatio": 0
    },
    "skirmishScore": {
      "1": "",
      "2": "",
      "3": ""
    }
  },
  "1": {
    "serverName": "Augury Rock",
    "idWorld": 2103,
    "date": "23/09/2022",
    "time": "21:49:12",
    "worldColor": "green",
    "nbKills": 1176,
    "nbDeaths": 1520,
    "ratio": 0.7736842105263158,
    "skirmishKills": 0,
    "skirmishDeaths": 0,
    "skirmishRatio": 0,
    "Center": {
      "nbKills": 59,
      "nbDeaths": 283,
      "ratio": 0.208,
      "skirmishKills": 0,
      "skirmishDeaths": 0,
      "skirmishRatio": 0
    },
    "RedHome": {
      "nbKills": 262,
      "nbDeaths": 418,
      "ratio": 0.627,
      "skirmishKills": 0,
      "skirmishDeaths": 0,
      "skirmishRatio": 0
    },
    "BlueHome": {
      "nbKills": 405,
      "nbDeaths": 344,
      "ratio": 1.177,
      "skirmishKills": 0,
      "skirmishDeaths": 0,
      "skirmishRatio": 0
    },
    "GreenHome": {
      "nbKills": 450,
      "nbDeaths": 475,
      "ratio": 0.947,
      "skirmishKills": 0,
      "skirmishDeaths": 0,
      "skirmishRatio": 0
    },
    "skirmishScore": {
      "1": "blue",
      "2": "red",
      "3": "green"
    }
  },
  "2": {
    "serverName": "Augury Rock",
    "idWorld": 2103,
    "date": "23/09/2022",
    "time": "23:51:55",
    "worldColor": "green",
    "nbKills": 2455,
    "nbDeaths": 3132,
    "ratio": 0.7838441890166028,
    "skirmishKills": 1279,
    "skirmishDeaths": 1612,
    "skirmishRatio": 0.793424317617866,
    "Center": {
      "nbKills": 269,
      "nbDeaths": 790,
      "ratio": 0.341,
      "skirmishKills": 210,
      "skirmishDeaths": 507,
      "skirmishRatio": 0.41420118343195267
    },
    "RedHome": {
      "nbKills": 597,
      "nbDeaths": 625,
      "ratio": 0.955,
      "skirmishKills": 335,
      "skirmishDeaths": 207,
      "skirmishRatio": 1.6183574879227054
    },
    "BlueHome": {
      "nbKills": 872,
      "nbDeaths": 931,
      "ratio": 0.937,
      "skirmishKills": 467,
      "skirmishDeaths": 587,
      "skirmishRatio": 0.7955706984667802
    },
    "GreenHome": {
      "nbKills": 717,
      "nbDeaths": 786,
      "ratio": 0.912,
      "skirmishKills": 267,
      "skirmishDeaths": 311,
      "skirmishRatio": 0.8585209003215434
    },
    "skirmishScore": {
      "1": "blue",
      "2": "green",
      "3": "red"
    }
  },
  "3": {
    "serverName": "Augury Rock",
    "idWorld": 2103,
    "date": "24/09/2022",
    "time": "01:58:21",
    "worldColor": "green",
    "nbKills": 2584,
    "nbDeaths": 3489,
    "ratio": 0.7406133562625394,
    "skirmishKills": 129,
    "skirmishDeaths": 357,
    "skirmishRatio": 0.36134453781512604,
    "Center": {
      "nbKills": 309,
      "nbDeaths": 947,
      "ratio": 0.326,
      "skirmishKills": 40,
      "skirmishDeaths": 157,
      "skirmishRatio": 0.25477707006369427
    },
    "RedHome": {
      "nbKills": 620,
      "nbDeaths": 659,
      "ratio": 0.941,
      "skirmishKills": 23,
      "skirmishDeaths": 34,
      "skirmishRatio": 0.6764705882352942
    },
    "BlueHome": {
      "nbKills": 919,
      "nbDeaths": 1059,
      "ratio": 0.868,
      "skirmishKills": 47,
      "skirmishDeaths": 128,
      "skirmishRatio": 0.3671875
    },
    "GreenHome": {
      "nbKills": 736,
      "nbDeaths": 824,
      "ratio": 0.893,
      "skirmishKills": 19,
      "skirmishDeaths": 38,
      "skirmishRatio": 0.5
    },
    "skirmishScore": {
      "1": "blue",
      "2": "green",
      "3": "red"
    }
  },
  "5": {
    "serverName": "Augury Rock",
    "idWorld": 2103,
    "date": "24/09/2022",
    "time": "06:06:09",
    "worldColor": "green",
    "nbKills": 2678,
    "nbDeaths": 3639,
    "ratio": 0.7359164605660896,
    "skirmishKills": 0,
    "skirmishDeaths": 0,
    "skirmishRatio": 0,
    "Center": {
      "nbKills": 365,
      "nbDeaths": 1005,
      "ratio": 0.363,
      "skirmishKills": 0,
      "skirmishDeaths": 0,
      "skirmishRatio": 0
    },
    "RedHome": {
      "nbKills": 627,
      "nbDeaths": 676,
      "ratio": 0.928,
      "skirmishKills": 0,
      "skirmishDeaths": 0,
      "skirmishRatio": 0
    },
    "BlueHome": {
      "nbKills": 935,
      "nbDeaths": 1110,
      "ratio": 0.842,
      "skirmishKills": 0,
      "skirmishDeaths": 0,
      "skirmishRatio": 0
    },
    "GreenHome": {
      "nbKills": 751,
      "nbDeaths": 848,
      "ratio": 0.886,
      "skirmishKills": 0,
      "skirmishDeaths": 0,
      "skirmishRatio": 0
    },
    "skirmishScore": {
      "1": "green",
      "2": "red",
      "3": "blue"
    }
  },
  "6": {
    "serverName": "Augury Rock",
    "idWorld": 2103,
    "date": "24/09/2022",
    "time": "08:04:15",
    "worldColor": "green",
    "nbKills": 2734,
    "nbDeaths": 3782,
    "ratio": 0.7228979375991539,
    "skirmishKills": 56,
    "skirmishDeaths": 143,
    "skirmishRatio": 0.3916083916083916,
    "Center": {
      "nbKills": 386,
      "nbDeaths": 1088,
      "ratio": 0.355,
      "skirmishKills": 21,
      "skirmishDeaths": 83,
      "skirmishRatio": 0.25301204819277107
    },
    "RedHome": {
      "nbKills": 631,
      "nbDeaths": 694,
      "ratio": 0.909,
      "skirmishKills": 4,
      "skirmishDeaths": 18,
      "skirmishRatio": 0.2222222222222222
    },
    "BlueHome": {
      "nbKills": 948,
      "nbDeaths": 1134,
      "ratio": 0.836,
      "skirmishKills": 13,
      "skirmishDeaths": 24,
      "skirmishRatio": 0.5416666666666666
    },
    "GreenHome": {
      "nbKills": 769,
      "nbDeaths": 866,
      "ratio": 0.888,
      "skirmishKills": 18,
      "skirmishDeaths": 18,
      "skirmishRatio": 1.0
    },
    "skirmishScore": {
      "1": "green",
      "2": "red",
      "3": "blue"
    }
  },
  "7": {
    "serverName": "Augury Rock",
    "idWorld": 2103,
    "date": "24/09/2022",
    "time": "09:49:49",
    "worldColor": "green",
    "nbKills": 2778,
    "nbDeaths": 3886,
    "ratio": 0.7148739063304169,
    "skirmishKills": 44,
    "skirmishDeaths": 104,
    "skirmishRatio": 0.4230769230769231,
    "Center": {
      "nbKills": 401,
      "nbDeaths": 1152,
      "ratio": 0.348,
      "skirmishKills": 15,
      "skirmishDeaths": 64,
      "skirmishRatio": 0.234375
    },
    "RedHome": {
      "nbKills": 636,
      "nbDeaths": 705,
      "ratio": 0.902,
      "skirmishKills": 5,
      "skirmishDeaths": 11,
      "skirmishRatio": 0.45454545454545453
    },
    "BlueHome": {
      "nbKills": 955,
      "nbDeaths": 1156,
      "ratio": 0.826,
      "skirmishKills": 7,
      "skirmishDeaths": 22,
      "skirmishRatio": 0.3181818181818182
    },
    "GreenHome": {
      "nbKills": 786,
      "nbDeaths": 873,
      "ratio": 0.9,
      "skirmishKills": 17,
      "skirmishDeaths": 7,
      "skirmishRatio": 2.4285714285714284
    },
    "skirmishScore": {
      "1": "green",
      "2": "blue",
      "3": "red"
    }
  },
  "8": {
    "serverName": "Augury Rock",
    "idWorld": 2103,
    "date": "24/09/2022",
    "time": "11:52:07",
    "worldColor": "green",
    "nbKills": 3516,
    "nbDeaths": 4515,
    "ratio": 0.7787375415282392,
    "skirmishKills": 738,
    "skirmishDeaths": 629,
    "skirmishRatio": 1.1732909379968204,
    "Center": {
      "nbKills": 826,
      "nbDeaths": 1442,
      "ratio": 0.573,
      "skirmishKills": 425,
      "skirmishDeaths": 290,
      "skirmishRatio": 1.4655172413793103
    },
    "RedHome": {
      "nbKills": 718,
      "nbDeaths": 814,
      "ratio": 0.882,
      "skirmishKills": 82,
      "skirmishDeaths": 109,
      "skirmishRatio": 0.7522935779816514
    },
    "BlueHome": {
      "nbKills": 1060,
      "nbDeaths": 1323,
      "ratio": 0.801,
      "skirmishKills": 105,
      "skirmishDeaths": 167,
      "skirmishRatio": 0.6287425149700598
    },
    "GreenHome": {
      "nbKills": 912,
      "nbDeaths": 936,
      "ratio": 0.974,
      "skirmishKills": 126,
      "skirmishDeaths": 63,
      "skirmishRatio": 2.0
    },
    "skirmishScore": {
      "1": "green",
      "2": "red",
      "3": "blue"
    }
  },
  "9": {
    "serverName": "Augury Rock",
    "idWorld": 2103,
    "date": "24/09/2022",
    "time": "13:48:59",
    "worldColor": "green",
    "nbKills": 4277,
    "nbDeaths": 5423,
    "ratio": 0.7886778535865757,
    "skirmishKills": 761,
    "skirmishDeaths": 908,
    "skirmishRatio": 0.8381057268722467,
    "Center": {
      "nbKills": 1156,
      "nbDeaths": 1843,
      "ratio": 0.627,
      "skirmishKills": 330,
      "skirmishDeaths": 401,
      "skirmishRatio": 0.8229426433915212
    },
    "RedHome": {
      "nbKills": 762,
      "nbDeaths": 865,
      "ratio": 0.881,
      "skirmishKills": 44,
      "skirmishDeaths": 51,
      "skirmishRatio": 0.8627450980392157
    },
    "BlueHome": {
      "nbKills": 1268,
      "nbDeaths": 1689,
      "ratio": 0.751,
      "skirmishKills": 208,
      "skirmishDeaths": 366,
      "skirmishRatio": 0.5683060109289617
    },
    "GreenHome": {
      "nbKills": 1091,
      "nbDeaths": 1026,
      "ratio": 1.063,
      "skirmishKills": 179,
      "skirmishDeaths": 90,
      "skirmishRatio": 1.988888888888889
    },
    "skirmishScore": {
      "1": "red",
      "2": "green",
      "3": "blue"
    }
  },
  "10": {
    "serverName": "Augury Rock",
    "idWorld": 2103,
    "date": "24/09/2022",
    "time": "15:55:56",
    "worldColor": "green",
    "nbKills": 4789,
    "nbDeaths": 5954,
    "ratio": 0.804333221363789,
    "skirmishKills": 512,
    "skirmishDeaths": 531,
    "skirmishRatio": 0.9642184557438794,
    "Center": {
      "nbKills": 1419,
      "nbDeaths": 2159,
      "ratio": 0.657,
      "skirmishKills": 263,
      "skirmishDeaths": 316,
      "skirmishRatio": 0.8322784810126582
    },
    "RedHome": {
      "nbKills": 775,
      "nbDeaths": 882,
      "ratio": 0.879,
      "skirmishKills": 13,
      "skirmishDeaths": 17,
      "skirmishRatio": 0.7647058823529411
    },
    "BlueHome": {
      "nbKills": 1371,
      "nbDeaths": 1828,
      "ratio": 0.75,
      "skirmishKills": 103,
      "skirmishDeaths": 139,
      "skirmishRatio": 0.7410071942446043
    },
    "GreenHome": {
      "nbKills": 1224,
      "nbDeaths": 1085,
      "ratio": 1.128,
      "skirmishKills": 133,
      "skirmishDeaths": 59,
      "skirmishRatio": 2.2542372881355934
    },
    "skirmishScore": {
      "1": "green",
      "2": "red",
      "3": "blue"
    }
  },
  "11": {
    "serverName": "Augury Rock",
    "idWorld": 2103,
    "date": "24/09/2022",
    "time": "17:54:02",
    "worldColor": "green",
    "nbKills": 6273,
    "nbDeaths": 7643,
    "ratio": 0.8207510139997384,
    "skirmishKills": 1484,
    "skirmishDeaths": 1689,
    "skirmishRatio": 0.8786264061574897,
    "Center": {
      "nbKills": 1609,
      "nbDeaths": 2775,
      "ratio": 0.58,
      "skirmishKills": 190,
      "skirmishDeaths": 616,
      "skirmishRatio": 0.30844155844155846
    },
    "RedHome": {
      "nbKills": 1148,
      "nbDeaths": 1092,
      "ratio": 1.051,
      "skirmishKills": 373,
      "skirmishDeaths": 210,
      "skirmishRatio": 1.776190476190476
    },
    "BlueHome": {
      "nbKills": 2126,
      "nbDeaths": 2480,
      "ratio": 0.857,
      "skirmishKills": 755,
      "skirmishDeaths": 652,
      "skirmishRatio": 1.1579754601226995
    },
    "GreenHome": {
      "nbKills": 1390,
      "nbDeaths": 1296,
      "ratio": 1.073,
      "skirmishKills": 166,
      "skirmishDeaths": 211,
      "skirmishRatio": 0.7867298578199052
    },
    "skirmishScore": {
      "1": "green",
      "2": "red",
      "3": "blue"
    }
  },
  "12": {
    "serverName": "Augury Rock",
    "idWorld": 2103,
    "date": "24/09/2022",
    "time": "19:52:03",
    "worldColor": "green",
    "nbKills": 7022,
    "nbDeaths": 9018,
    "ratio": 0.7786648924373475,
    "skirmishKills": 749,
    "skirmishDeaths": 1375,
    "skirmishRatio": 0.5447272727272727,
    "Center": {
      "nbKills": 1818,
      "nbDeaths": 3225,
      "ratio": 0.564,
      "skirmishKills": 209,
      "skirmishDeaths": 450,
      "skirmishRatio": 0.46444444444444444
    },
    "RedHome": {
      "nbKills": 1318,
      "nbDeaths": 1176,
      "ratio": 1.121,
      "skirmishKills": 170,
      "skirmishDeaths": 84,
      "skirmishRatio": 2.0238095238095237
    },
    "BlueHome": {
      "nbKills": 2423,
      "nbDeaths": 3247,
      "ratio": 0.746,
      "skirmishKills": 297,
      "skirmishDeaths": 767,
      "skirmishRatio": 0.38722294654498046
    },
    "GreenHome": {
      "nbKills": 1463,
      "nbDeaths": 1370,
      "ratio": 1.068,
      "skirmishKills": 73,
      "skirmishDeaths": 74,
      "skirmishRatio": 0.9864864864864865
    },
    "skirmishScore": {
      "1": "green",
      "2": "red",
      "3": "blue"
    }
  },
  "13": {
    "serverName": "Augury Rock",
    "idWorld": 2103,
    "date": "24/09/2022",
    "time": "21:48:51",
    "worldColor": "green",
    "nbKills": 7729,
    "nbDeaths": 10289,
    "ratio": 0.751190591894256,
    "skirmishKills": 707,
    "skirmishDeaths": 1271,
    "skirmishRatio": 0.5562549173878836,
    "Center": {
      "nbKills": 2041,
      "nbDeaths": 3711,
      "ratio": 0.55,
      "skirmishKills": 223,
      "skirmishDeaths": 486,
      "skirmishRatio": 0.4588477366255144
    },
    "RedHome": {
      "nbKills": 1390,
      "nbDeaths": 1307,
      "ratio": 1.064,
      "skirmishKills": 72,
      "skirmishDeaths": 131,
      "skirmishRatio": 0.549618320610687
    },
    "BlueHome": {
      "nbKills": 2641,
      "nbDeaths": 3669,
      "ratio": 0.72,
      "skirmishKills": 218,
      "skirmishDeaths": 422,
      "skirmishRatio": 0.5165876777251185
    },
    "GreenHome": {
      "nbKills": 1657,
      "nbDeaths": 1602,
      "ratio": 1.034,
      "skirmishKills": 194,
      "skirmishDeaths": 232,
      "skirmishRatio": 0.8362068965517241
    },
    "skirmishScore": {
      "1": "blue",
      "2": "green",
      "3": "red"
    }
  },
  "14": {
    "serverName": "Augury Rock",
    "idWorld": 2103,
    "date": "24/09/2022",
    "time": "23:50:58",
    "worldColor": "green",
    "nbKills": 8623,
    "nbDeaths": 11634,
    "ratio": 0.7411896166408802,
    "skirmishKills": 894,
    "skirmishDeaths": 1345,
    "skirmishRatio": 0.6646840148698885,
    "Center": {
      "nbKills": 2209,
      "nbDeaths": 4123,
      "ratio": 0.536,
      "skirmishKills": 168,
      "skirmishDeaths": 412,
      "skirmishRatio": 0.4077669902912621
    },
    "RedHome": {
      "nbKills": 1478,
      "nbDeaths": 1350,
      "ratio": 1.095,
      "skirmishKills": 88,
      "skirmishDeaths": 43,
      "skirmishRatio": 2.046511627906977
    },
    "BlueHome": {
      "nbKills": 2792,
      "nbDeaths": 3848,
      "ratio": 0.726,
      "skirmishKills": 151,
      "skirmishDeaths": 179,
      "skirmishRatio": 0.8435754189944135
    },
    "GreenHome": {
      "nbKills": 2144,
      "nbDeaths": 2313,
      "ratio": 0.927,
      "skirmishKills": 487,
      "skirmishDeaths": 711,
      "skirmishRatio": 0.6849507735583685
    },
    "skirmishScore": {
      "1": "blue",
      "2": "green",
      "3": "red"
    }
  },
  "15": {
    "serverName": "Augury Rock",
    "idWorld": 2103,
    "date": "25/09/2022",
    "time": "01:56:35",
    "worldColor": "green",
    "nbKills": 9230,
    "nbDeaths": 12056,
    "ratio": 0.7655938951559389,
    "skirmishKills": 607,
    "skirmishDeaths": 422,
    "skirmishRatio": 1.438388625592417,
    "Center": {
      "nbKills": 2627,
      "nbDeaths": 4365,
      "ratio": 0.602,
      "skirmishKills": 418,
      "skirmishDeaths": 242,
      "skirmishRatio": 1.7272727272727273
    },
    "RedHome": {
      "nbKills": 1503,
      "nbDeaths": 1384,
      "ratio": 1.086,
      "skirmishKills": 25,
      "skirmishDeaths": 34,
      "skirmishRatio": 0.7352941176470589
    },
    "BlueHome": {
      "nbKills": 2805,
      "nbDeaths": 3900,
      "ratio": 0.719,
      "skirmishKills": 13,
      "skirmishDeaths": 52,
      "skirmishRatio": 0.25
    },
    "GreenHome": {
      "nbKills": 2295,
      "nbDeaths": 2407,
      "ratio": 0.953,
      "skirmishKills": 151,
      "skirmishDeaths": 94,
      "skirmishRatio": 1.6063829787234043
    },
    "skirmishScore": {
      "1": "blue",
      "2": "green",
      "3": "red"
    }
  },
  "17": {
    "serverName": "Augury Rock",
    "idWorld": 2103,
    "date": "25/09/2022",
    "time": "05:59:18",
    "worldColor": "green",
    "nbKills": 9344,
    "nbDeaths": 12342,
    "ratio": 0.757089612704586,
    "skirmishKills": 0,
    "skirmishDeaths": 0,
    "skirmishRatio": 0,
    "Center": {
      "nbKills": 2661,
      "nbDeaths": 4441,
      "ratio": 0.599,
      "skirmishKills": 0,
      "skirmishDeaths": 0,
      "skirmishRatio": 0
    },
    "RedHome": {
      "nbKills": 1510,
      "nbDeaths": 1392,
      "ratio": 1.085,
      "skirmishKills": 0,
      "skirmishDeaths": 0,
      "skirmishRatio": 0
    },
    "BlueHome": {
      "nbKills": 2839,
      "nbDeaths": 3948,
      "ratio": 0.719,
      "skirmishKills": 0,
      "skirmishDeaths": 0,
      "skirmishRatio": 0
    },
    "GreenHome": {
      "nbKills": 2334,
      "nbDeaths": 2561,
      "ratio": 0.911,
      "skirmishKills": 0,
      "skirmishDeaths": 0,
      "skirmishRatio": 0
    },
    "skirmishScore": {
      "1": "green",
      "2": "red",
      "3": "blue"
    }
  },
  "18": {
    "serverName": "Augury Rock",
    "idWorld": 2103,
    "date": "25/09/2022",
    "time": "08:01:08",
    "worldColor": "green",
    "nbKills": 9393,
    "nbDeaths": 12431,
    "ratio": 0.7556109725685786,
    "skirmishKills": 49,
    "skirmishDeaths": 89,
    "skirmishRatio": 0.550561797752809,
    "Center": {
      "nbKills": 2672,
      "nbDeaths": 4448,
      "ratio": 0.601,
      "skirmishKills": 11,
      "skirmishDeaths": 7,
      "skirmishRatio": 1.5714285714285714
    },
    "RedHome": {
      "nbKills": 1514,
      "nbDeaths": 1395,
      "ratio": 1.085,
      "skirmishKills": 4,
      "skirmishDeaths": 3,
      "skirmishRatio": 1.3333333333333333
    },
    "BlueHome": {
      "nbKills": 2850,
      "nbDeaths": 3979,
      "ratio": 0.716,
      "skirmishKills": 11,
      "skirmishDeaths": 31,
      "skirmishRatio": 0.3548387096774194
    },
    "GreenHome": {
      "nbKills": 2357,
      "nbDeaths": 2609,
      "ratio": 0.903,
      "skirmishKills": 23,
      "skirmishDeaths": 48,
      "skirmishRatio": 0.4791666666666667
    },
    "skirmishScore": {
      "1": "blue",
      "2": "green",
      "3": "red"
    }
  },
  "19": {
    "serverName": "Augury Rock",
    "idWorld": 2103,
    "date": "25/09/2022",
    "time": "09:49:19",
    "worldColor": "green",
    "nbKills": 9524,
    "nbDeaths": 12742,
    "ratio": 0.7474493800031392,
    "skirmishKills": 131,
    "skirmishDeaths": 311,
    "skirmishRatio": 0.4212218649517685,
    "Center": {
      "nbKills": 2704,
      "nbDeaths": 4596,
      "ratio": 0.588,
      "skirmishKills": 32,
      "skirmishDeaths": 148,
      "skirmishRatio": 0.21621621621621623
    },
    "RedHome": {
      "nbKills": 1520,
      "nbDeaths": 1436,
      "ratio": 1.058,
      "skirmishKills": 6,
      "skirmishDeaths": 41,
      "skirmishRatio": 0.14634146341463414
    },
    "BlueHome": {
      "nbKills": 2874,
      "nbDeaths": 4070,
      "ratio": 0.706,
      "skirmishKills": 24,
      "skirmishDeaths": 91,
      "skirmishRatio": 0.26373626373626374
    },
    "GreenHome": {
      "nbKills": 2426,
      "nbDeaths": 2640,
      "ratio": 0.919,
      "skirmishKills": 69,
      "skirmishDeaths": 31,
      "skirmishRatio": 2.225806451612903
    },
    "skirmishScore": {
      "1": "blue",
      "2": "green",
      "3": "red"
    }
  },
  "20": {
    "serverName": "Augury Rock",
    "idWorld": 2103,
    "date": "25/09/2022",
    "time": "11:52:26",
    "worldColor": "green",
    "nbKills": 10447,
    "nbDeaths": 13245,
    "ratio": 0.7887504718761796,
    "skirmishKills": 923,
    "skirmishDeaths": 503,
    "skirmishRatio": 1.8349900596421471,
    "Center": {
      "nbKills": 3350,
      "nbDeaths": 4861,
      "ratio": 0.689,
      "skirmishKills": 646,
      "skirmishDeaths": 265,
      "skirmishRatio": 2.4377358490566037
    },
    "RedHome": {
      "nbKills": 1553,
      "nbDeaths": 1495,
      "ratio": 1.039,
      "skirmishKills": 33,
      "skirmishDeaths": 59,
      "skirmishRatio": 0.559322033898305
    },
    "BlueHome": {
      "nbKills": 2935,
      "nbDeaths": 4120,
      "ratio": 0.712,
      "skirmishKills": 61,
      "skirmishDeaths": 50,
      "skirmishRatio": 1.22
    },
    "GreenHome": {
      "nbKills": 2609,
      "nbDeaths": 2769,
      "ratio": 0.942,
      "skirmishKills": 183,
      "skirmishDeaths": 129,
      "skirmishRatio": 1.4186046511627908
    },
    "skirmishScore": {
      "1": "green",
      "2": "blue",
      "3": "red"
    }
  },
  "21": {
    "serverName": "Augury Rock",
    "idWorld": 2103,
    "date": "25/09/2022",
    "time": "13:49:02",
    "worldColor": "green",
    "nbKills": 10885,
    "nbDeaths": 13694,
    "ratio": 0.7948736672995472,
    "skirmishKills": 438,
    "skirmishDeaths": 449,
    "skirmishRatio": 0.9755011135857461,
    "Center": {
      "nbKills": 3488,
      "nbDeaths": 5057,
      "ratio": 0.69,
      "skirmishKills": 138,
      "skirmishDeaths": 196,
      "skirmishRatio": 0.7040816326530612
    },
    "RedHome": {
      "nbKills": 1572,
      "nbDeaths": 1535,
      "ratio": 1.024,
      "skirmishKills": 19,
      "skirmishDeaths": 40,
      "skirmishRatio": 0.475
    },
    "BlueHome": {
      "nbKills": 2992,
      "nbDeaths": 4169,
      "ratio": 0.718,
      "skirmishKills": 57,
      "skirmishDeaths": 49,
      "skirmishRatio": 1.163265306122449
    },
    "GreenHome": {
      "nbKills": 2833,
      "nbDeaths": 2933,
      "ratio": 0.966,
      "skirmishKills": 224,
      "skirmishDeaths": 164,
      "skirmishRatio": 1.3658536585365855
    },
    "skirmishScore": {
      "1": "green",
      "2": "red",
      "3": "blue"
    }
  },
  "22": {
    "serverName": "Augury Rock",
    "idWorld": 2103,
    "date": "25/09/2022",
    "time": "15:55:57",
    "worldColor": "green",
    "nbKills": 11498,
    "nbDeaths": 14416,
    "ratio": 0.7975860155382908,
    "skirmishKills": 613,
    "skirmishDeaths": 722,
    "skirmishRatio": 0.8490304709141274,
    "Center": {
      "nbKills": 3659,
      "nbDeaths": 5499,
      "ratio": 0.665,
      "skirmishKills": 171,
      "skirmishDeaths": 442,
      "skirmishRatio": 0.38687782805429866
    },
    "RedHome": {
      "nbKills": 1614,
      "nbDeaths": 1620,
      "ratio": 0.996,
      "skirmishKills": 42,
      "skirmishDeaths": 85,
      "skirmishRatio": 0.49411764705882355
    },
    "BlueHome": {
      "nbKills": 3316,
      "nbDeaths": 4293,
      "ratio": 0.772,
      "skirmishKills": 324,
      "skirmishDeaths": 124,
      "skirmishRatio": 2.6129032258064515
    },
    "GreenHome": {
      "nbKills": 2909,
      "nbDeaths": 3004,
      "ratio": 0.968,
      "skirmishKills": 76,
      "skirmishDeaths": 71,
      "skirmishRatio": 1.0704225352112675
    },
    "skirmishScore": {
      "1": "green",
      "2": "red",
      "3": "blue"
    }
  },
  "23": {
    "serverName": "Augury Rock",
    "idWorld": 2103,
    "date": "25/09/2022",
    "time": "17:54:49",
    "worldColor": "green",
    "nbKills": 12777,
    "nbDeaths": 15420,
    "ratio": 0.8285992217898833,
    "skirmishKills": 1279,
    "skirmishDeaths": 1004,
    "skirmishRatio": 1.2739043824701195,
    "Center": {
      "nbKills": 3829,
      "nbDeaths": 5893,
      "ratio": 0.65,
      "skirmishKills": 170,
      "skirmishDeaths": 394,
      "skirmishRatio": 0.43147208121827413
    },
    "RedHome": {
      "nbKills": 1749,
      "nbDeaths": 1776,
      "ratio": 0.985,
      "skirmishKills": 135,
      "skirmishDeaths": 156,
      "skirmishRatio": 0.8653846153846154
    },
    "BlueHome": {
      "nbKills": 3982,
      "nbDeaths": 4517,
      "ratio": 0.882,
      "skirmishKills": 666,
      "skirmishDeaths": 224,
      "skirmishRatio": 2.9732142857142856
    },
    "GreenHome": {
      "nbKills": 3217,
      "nbDeaths": 3234,
      "ratio": 0.995,
      "skirmishKills": 308,
      "skirmishDeaths": 230,
      "skirmishRatio": 1.3391304347826087
    },
    "skirmishScore": {
      "1": "green",
      "2": "red",
      "3": "blue"
    }
  },
  "24": {
    "serverName": "Augury Rock",
    "idWorld": 2103,
    "date": "25/09/2022",
    "time": "19:52:29",
    "worldColor": "green",
    "nbKills": 13156,
    "nbDeaths": 16160,
    "ratio": 0.814108910891089,
    "skirmishKills": 379,
    "skirmishDeaths": 740,
    "skirmishRatio": 0.5121621621621621,
    "Center": {
      "nbKills": 3887,
      "nbDeaths": 6065,
      "ratio": 0.641,
      "skirmishKills": 58,
      "skirmishDeaths": 172,
      "skirmishRatio": 0.3372093023255814
    },
    "RedHome": {
      "nbKills": 1788,
      "nbDeaths": 1837,
      "ratio": 0.973,
      "skirmishKills": 39,
      "skirmishDeaths": 61,
      "skirmishRatio": 0.639344262295082
    },
    "BlueHome": {
      "nbKills": 4078,
      "nbDeaths": 4799,
      "ratio": 0.85,
      "skirmishKills": 96,
      "skirmishDeaths": 282,
      "skirmishRatio": 0.3404255319148936
    },
    "GreenHome": {
      "nbKills": 3403,
      "nbDeaths": 3459,
      "ratio": 0.984,
      "skirmishKills": 186,
      "skirmishDeaths": 225,
      "skirmishRatio": 0.8266666666666667
    },
    "skirmishScore": {
      "1": "blue",
      "2": "red",
      "3": "green"
    }
  }
}