{
  "0": {
    "serverName": "Augury Rock",
    "idWorld": 2103,
    "date": "10/02/2023",
    "time": "20:48:49",
    "worldColor": "red",
    "nbKills": 0,
    "nbDeaths": 0,
    "ratio": 0,
    "skirmishKills": 0,
    "skirmishDeaths": 0,
    "skirmishRatio": 0,
    "Center": {
      "nbKills": 0,
      "nbDeaths": 0,
      "ratio": 0,
      "skirmishKills": 0,
      "skirmishDeaths": 0,
      "skirmishRatio": 0
    },
    "RedHome": {
      "nbKills": 0,
      "nbDeaths": 0,
      "ratio": 0,
      "skirmishKills": 0,
      "skirmishDeaths": 0,
      "skirmishRatio": 0
    },
    "BlueHome": {
      "nbKills": 0,
      "nbDeaths": 0,
      "ratio": 0,
      "skirmishKills": 0,
      "skirmishDeaths": 0,
      "skirmishRatio": 0
    },
    "GreenHome": {
      "nbKills": 0,
      "nbDeaths": 0,
      "ratio": 0,
      "skirmishKills": 0,
      "skirmishDeaths": 0,
      "skirmishRatio": 0
    },
    "skirmishScore": {
      "1": "blue",
      "2": "red",
      "3": "green"
    }
  },
  "1": {
    "serverName": "Augury Rock",
    "idWorld": 2103,
    "date": "10/02/2023",
    "time": "22:48:53",
    "worldColor": "red",
    "nbKills": 2297,
    "nbDeaths": 2126,
    "ratio": 1.0804327375352776,
    "skirmishKills": 2297,
    "skirmishDeaths": 2126,
    "skirmishRatio": 1.0804327375352776,
    "Center": {
      "nbKills": 754,
      "nbDeaths": 683,
      "ratio": 1.104,
      "skirmishKills": 754,
      "skirmishDeaths": 683,
      "skirmishRatio": 1.1039531478770133
    },
    "RedHome": {
      "nbKills": 338,
      "nbDeaths": 266,
      "ratio": 1.271,
      "skirmishKills": 338,
      "skirmishDeaths": 266,
      "skirmishRatio": 1.2706766917293233
    },
    "BlueHome": {
      "nbKills": 224,
      "nbDeaths": 283,
      "ratio": 0.792,
      "skirmishKills": 224,
      "skirmishDeaths": 283,
      "skirmishRatio": 0.7915194346289752
    },
    "GreenHome": {
      "nbKills": 981,
      "nbDeaths": 894,
      "ratio": 1.097,
      "skirmishKills": 981,
      "skirmishDeaths": 894,
      "skirmishRatio": 1.0973154362416107
    },
    "skirmishScore": {
      "1": "blue",
      "2": "red",
      "3": "green"
    }
  },
  "2": {
    "serverName": "Augury Rock",
    "idWorld": 2103,
    "date": "11/02/2023",
    "time": "00:48:54",
    "worldColor": "red",
    "nbKills": 3445,
    "nbDeaths": 3125,
    "ratio": 1.1024,
    "skirmishKills": 1148,
    "skirmishDeaths": 999,
    "skirmishRatio": 1.1491491491491492,
    "Center": {
      "nbKills": 1459,
      "nbDeaths": 1156,
      "ratio": 1.262,
      "skirmishKills": 705,
      "skirmishDeaths": 473,
      "skirmishRatio": 1.4904862579281184
    },
    "RedHome": {
      "nbKills": 569,
      "nbDeaths": 497,
      "ratio": 1.145,
      "skirmishKills": 231,
      "skirmishDeaths": 231,
      "skirmishRatio": 1.0
    },
    "BlueHome": {
      "nbKills": 332,
      "nbDeaths": 455,
      "ratio": 0.73,
      "skirmishKills": 108,
      "skirmishDeaths": 172,
      "skirmishRatio": 0.627906976744186
    },
    "GreenHome": {
      "nbKills": 1085,
      "nbDeaths": 1017,
      "ratio": 1.067,
      "skirmishKills": 104,
      "skirmishDeaths": 123,
      "skirmishRatio": 0.8455284552845529
    },
    "skirmishScore": {
      "1": "red",
      "2": "blue",
      "3": "green"
    }
  },
  "3": {
    "serverName": "Augury Rock",
    "idWorld": 2103,
    "date": "11/02/2023",
    "time": "03:33:35",
    "worldColor": "red",
    "nbKills": 3910,
    "nbDeaths": 3574,
    "ratio": 1.094012311135982,
    "skirmishKills": 465,
    "skirmishDeaths": 449,
    "skirmishRatio": 1.0356347438752784,
    "Center": {
      "nbKills": 1897,
      "nbDeaths": 1569,
      "ratio": 1.209,
      "skirmishKills": 438,
      "skirmishDeaths": 413,
      "skirmishRatio": 1.0605326876513317
    },
    "RedHome": {
      "nbKills": 583,
      "nbDeaths": 500,
      "ratio": 1.166,
      "skirmishKills": 14,
      "skirmishDeaths": 3,
      "skirmishRatio": 4.666666666666667
    },
    "BlueHome": {
      "nbKills": 343,
      "nbDeaths": 484,
      "ratio": 0.709,
      "skirmishKills": 11,
      "skirmishDeaths": 29,
      "skirmishRatio": 0.3793103448275862
    },
    "GreenHome": {
      "nbKills": 1087,
      "nbDeaths": 1021,
      "ratio": 1.065,
      "skirmishKills": 2,
      "skirmishDeaths": 4,
      "skirmishRatio": 0.5
    },
    "skirmishScore": {
      "1": "blue",
      "2": "red",
      "3": "green"
    }
  },
  "4": {
    "serverName": "Augury Rock",
    "idWorld": 2103,
    "date": "11/02/2023",
    "time": "04:49:08",
    "worldColor": "red",
    "nbKills": 3945,
    "nbDeaths": 3599,
    "ratio": 1.0961378160600166,
    "skirmishKills": 35,
    "skirmishDeaths": 25,
    "skirmishRatio": 1.4,
    "Center": {
      "nbKills": 1916,
      "nbDeaths": 1588,
      "ratio": 1.207,
      "skirmishKills": 19,
      "skirmishDeaths": 19,
      "skirmishRatio": 1.0
    },
    "RedHome": {
      "nbKills": 583,
      "nbDeaths": 501,
      "ratio": 1.164,
      "skirmishKills": 0,
      "skirmishDeaths": 1,
      "skirmishRatio": 0.0
    },
    "BlueHome": {
      "nbKills": 355,
      "nbDeaths": 487,
      "ratio": 0.729,
      "skirmishKills": 12,
      "skirmishDeaths": 3,
      "skirmishRatio": 4.0
    },
    "GreenHome": {
      "nbKills": 1091,
      "nbDeaths": 1023,
      "ratio": 1.066,
      "skirmishKills": 4,
      "skirmishDeaths": 2,
      "skirmishRatio": 2.0
    },
    "skirmishScore": {
      "1": "blue",
      "2": "red",
      "3": "green"
    }
  }
}